Metadata-Version: 1.1
Name: example-component
Version: 0.0.1
Summary: Project Description
Home-page: UNKNOWN
Author: Mitterrand Monteiro <mitterrand.monteiro@ext.chemtech.net.br>
Author-email: UNKNOWN
License: MIT
Platform: UNKNOWN
Classifier: Framework :: Dash
